{"ast":null,"code":"'use strict';\n\nfunction _typeof(obj) { \"@babel/helpers - typeof\"; return _typeof = \"function\" == typeof Symbol && \"symbol\" == typeof Symbol.iterator ? function (obj) { return typeof obj; } : function (obj) { return obj && \"function\" == typeof Symbol && obj.constructor === Symbol && obj !== Symbol.prototype ? \"symbol\" : typeof obj; }, _typeof(obj); }\n\nvar toStr = Object.prototype.toString;\n\nmodule.exports = function isArguments(value) {\n  var str = toStr.call(value);\n  var isArgs = str === '[object Arguments]';\n\n  if (!isArgs) {\n    isArgs = str !== '[object Array]' && value !== null && _typeof(value) === 'object' && typeof value.length === 'number' && value.length >= 0 && toStr.call(value.callee) === '[object Function]';\n  }\n\n  return isArgs;\n};","map":null,"metadata":{},"sourceType":"module"}